arxivextract/__init__.py
arxivextract/data.py
arxivextract/extraction.py
arxivextract/keywords.py
arxivextract-0.0.4.dist-info/licenses/LICENSE
arxivextract-0.0.4.dist-info/METADATA
arxivextract-0.0.4.dist-info/WHEEL
arxivextract-0.0.4.dist-info/top_level.txt
arxivextract-0.0.4.dist-info/RECORD
